MANIFEST.in
README.rst
setup.py
pyea/__init__.py
pyea.egg-info/PKG-INFO
pyea.egg-info/SOURCES.txt
pyea.egg-info/dependency_links.txt
pyea.egg-info/requires.txt
pyea.egg-info/top_level.txt
pyea/functions/__init__.py
pyea/functions/__pycache__/__init__.cpython-35.pyc
pyea/models/__init__.py
pyea/models/ga.py
pyea/models/__pycache__/__init__.cpython-35.pyc
pyea/models/__pycache__/ga.cpython-35.pyc