Metadata-Version: 1.1
Name: pyea
Version: 0.2
Summary: Set of pure python libraries including the most common evolutionary algorithms
Home-page: https://github.com/albahnsen/pyea
Author: Alejandro CORREA BAHNSEN
Author-email: al.bahnsen@gmail.com
License: new BSD
Keywords: optimization,evolutionary,genetic
Platform: UNKNOWN
Classifier: Intended Audience :: Science/Research
Classifier: Intended Audience :: Developers
Classifier: Programming Language :: Python
Classifier: Topic :: Software Development
Classifier: Topic :: Scientific/Engineering
Classifier: Programming Language :: Python :: 2.7
Classifier: Programming Language :: Python :: 3
Classifier: Programming Language :: Python :: 3.3
Classifier: Programming Language :: Python :: 3.4
Classifier: Programming Language :: Python :: 3.5
Classifier: Topic :: Scientific/Engineering :: Artificial Intelligence
Classifier: License :: OSI Approved :: BSD License
Classifier: Operating System :: OS Independent
